usim/__about__.py
usim/__init__.py
usim/typing.py
usim/_basics/__init__.py
usim/_basics/_resource_level.py
usim/_basics/pipe.py
usim/_basics/resource.py
usim/_basics/streams.py
usim/_basics/tracked.py
usim/_concurrent/__init__.py
usim/_concurrent/basics.py
usim/_core/__init__.py
usim/_core/handler.py
usim/_core/loop.py
usim/_core/waitq.py
usim/_primitives/__init__.py
usim/_primitives/concurrent_exception.py
usim/_primitives/condition.py
usim/_primitives/context.py
usim/_primitives/flag.py
usim/_primitives/locks.py
usim/_primitives/notification.py
usim/_primitives/task.py
usim/_primitives/timing.py
usim/py/__init__.py
usim/py/_awaitable.py
usim/py/core.py
usim/py/events.py
usim/py/exceptions.py
usim/py/resources/__init__.py
usim/py/resources/base.py
usim/py/resources/container.py
usim/py/resources/resource.py
usim/py/resources/store.py
usim-0.4.4.dist-info/LICENSE
usim-0.4.4.dist-info/WHEEL
usim-0.4.4.dist-info/METADATA
usim-0.4.4.dist-info/RECORD
