Metadata-Version: 2.1
Name: usim
Version: 0.4.4
Summary: Lightweight Simulation Framework
Home-page: https://github.com/MaineKuehn/usim
Keywords: simulation simpy event loop async coroutine
Author: Eileen Kuehn, Max Fischer
Author-email: mainekuehn@gmail.com
Classifier: Development Status :: 4 - Beta
Classifier: Intended Audience :: Developers
Classifier: License :: OSI Approved :: MIT License
Classifier: Programming Language :: Python :: 3 :: Only
Requires-Dist: sortedcontainers
Requires-Dist: asyncstdlib>=1.1.1
Requires-Dist: typing_extensions>=3.10.0
Requires-Dist: sphinx ; extra == "doc"
Requires-Dist: sphinx_rtd_theme ; extra == "doc"
Requires-Dist: sphinxcontrib-contentui ; extra == "doc"
Requires-Dist: sphinxcontrib-trio ; extra == "doc"
Requires-Dist: pytest >=4.3.0 ; extra == "test"
Requires-Dist: flake8 ; extra == "test"
Requires-Dist: flake8-bugbear ; extra == "test"
Requires-Dist: black ; extra == "test" and ( implementation_name=='cpython')
Project-URL: Documentation, https://usim.readthedocs.io
Provides-Extra: doc
Provides-Extra: test
